flake8_typechecking_import.py
flake8_typechecking_import-0.5.dist-info/entry_points.txt
flake8_typechecking_import-0.5.dist-info/LICENSE
flake8_typechecking_import-0.5.dist-info/WHEEL
flake8_typechecking_import-0.5.dist-info/METADATA
flake8_typechecking_import-0.5.dist-info/RECORD
