Metadata-Version: 2.1
Name: flake8_typechecking_import
Version: 0.5
Summary: A flake plugin that checks for typing.TYPE_CHECKING-able imports
Home-page: https://github.com/ingolemo/flake8-typechecking_import
Author: Adrian Room
Author-email: ingolemo@gmail.com
Requires-Python: >3.6
Classifier: License :: OSI Approved :: GNU General Public License v3 or later (GPLv3+)
Requires-Dist: flake8
Requires-Dist: dataclasses;python_version=="3.6"
Requires-Dist: black ; extra == "dev"
Requires-Dist: mypy ; extra == "dev"
Requires-Dist: tox ; extra == "dev"
Requires-Dist: pytest ; extra == "test"
Requires-Dist: pytest-sugar ; extra == "test"
Requires-Dist: pytest-coverage ; extra == "test"
Requires-Dist: coverage[toml] ; extra == "test"
Requires-Dist: types-dataclasses ; extra == "test"
Provides-Extra: dev
Provides-Extra: test
